Workbook

Sheet Library Guide
A1: Revenue Compass — ASC 606 Master Library
A2: AI guidance corpus + accountant study guide | Prepared 2026-09-04
A4: Purpose and operating principle
A5: Purpose | B5: This workbook is the controlled accounting-reference source for Revenue Compass. It is designed to help the future OpenAI layer retrieve relevant ASC 606 concepts, propose facts/judgments/rationales, and show source provenance. It is also a study guide for the project owner. It is not a substitute for reading the authoritative Codification and does not itself constitute professional accounting advice.
A6: Core principle | B6: AI interprets and proposes. The accountant reviews, edits, approves or overrides every material accounting judgment. Deterministic code performs authoritative monetary, date, allocation, catch-up, balance and journal calculations after approval.
A7: Status control | B7: Every guidance card begins as “Draft — user review required.” Change a card to Reviewed or Approved only after you have read the cited ASC paragraphs and supporting interpretation and are comfortable defending the summary. Populate Last Reviewed when that review occurs.
A9: Source hierarchy
A10: Level 1 — Authoritative | B10: FASB Accounting Standards Codification (ASC) paragraph references. FASB identifies the Codification as the single official source of authoritative nongovernmental U.S. GAAP. The library intentionally paraphrases rather than reproduces substantial Codification text.
A11: Level 2 — Interpretive | B11: Deloitte DART Revenue Recognition Roadmap / Technology Industry Accounting Guide and EY Financial Reporting Developments are nonauthoritative interpretive sources used to understand application and examples.
A12: Level 3 — Product policy | B12: Revenue Compass engine behavior records the project’s supported accounting mechanics and controls. Product limitations are not GAAP and should never be presented as GAAP requirements.
A14: How to use the Guidance Cards sheet
A15: One card = one decision | B15: Cards are organized around meaningful accounting decisions rather than one row per Codification paragraph. A card can therefore have one primary ASC reference and several related references.
A16: Facts Required | B16: Facts the AI/accountant should obtain before proposing a conclusion. Missing facts should produce “uncertain / accountant action required,” not invented assumptions.
A17: AI May Propose | B17: Defines what the AI is allowed to prepopulate. These are proposals only. Contract/source evidence should be retained with the AI draft.
A18: Accountant Must Approve | B18: Judgment fields that cannot become authoritative merely because the AI populated them.
A19: Engine Behavior | B19: What deterministic Revenue Compass code may do after the accounting judgment is approved. It deliberately separates judgment from calculation.
A21: Phase 5B readiness
A22: Variable consideration | B22: The workbook includes identification, expected-value and most-likely estimation, constraint, remeasurement, variable allocation exception, series-period usage, exact-ratio fixed-rate meters, SaaS/AI API examples and AR/billing separation. See “Phase 5B Map.”
A23: Scope boundary | B23: Phase 5B simple metered usage covers multiple fixed-rate amount-per-quantity meters when specific-series-period allocation is approved. Tiered pricing, annual minimum/overage constructs, cumulative volume discounts and complex true-ups are intentionally flagged for more advanced analysis rather than forced through the simple meter path.
A25: Recommended study sequence
A26: Sequence | B26: 1. Step 1 cards 1–10 2. Step 2 cards 11–24 3. Step 3 cards 25–43, especially cards 27–34 4. Step 4 cards 44–57, especially cards 52–57 5. Step 5 cards 58–77 6. Special-topic cards 78–116 7. Review the Phase 5B Map and reperform Case 7 independently.
A28: Core source links
A29: FASB Standards | B29: https://www.fasb.org/standards
A30: FASB ASC access | B30: https://asc.fasb.org/
A31: Deloitte Revenue Recognition Roadmap | B31: https://dart.deloitte.com/USDART/home/codification/revenue/asc606-10/roadmap-revenue-recognition
A32: Deloitte Technology Industry Accounting Guide | B32: https://dart.deloitte.com/USDART/home/publications/deloitte/industry/technology/technology-accounting-guide
A33: EY Revenue FRD | B33: https://www.ey.com/en_us/technical/accountinglink/financial-reporting-developments---revenue-from-contracts-with-c

Sheet Guidance Cards
A1: Revenue Compass — ASC 606 Guidance Cards
A2: Item No. | B2: Topic | C2: Subtopic | D2: Primary ASC Reference | E2: Related ASC References | F2: Rule Summary | G2: Decision Criteria | H2: Facts Required | I2: Important Nuances | J2: When Relevant | K2: AI May Propose | L2: Accountant Must Approve | M2: Revenue Compass Engine Behavior | N2: Interpretive Source | O2: Source URL(s) | P2: Retrieval Tags | Q2: Status | R2: Last Reviewed
A3: 1 | B3: Step 1 | C3: Contract Identification — Five Criteria | D3: ASC 606-10-25-1 | E3: ASC 606-10-25-2 through 25-8 | F3: An arrangement qualifies as a contract under ASC 606 only when the parties have approved it and are committed to perform, each party's rights and payment terms are identifiable, the arrangement has commercial substance, and collection of the consideration expected in exchange for the promised goods or services is probable. | G3: 1. Contract is approved and parties are committed. 2. Rights to goods or services are identifiable. 3. Payment terms are identifiable. 4. The arrangement has commercial substance. 5. Collection of substantially all consideration to which the entity expects to be entitled is probable. | H3: Executed contract/order form; evidence of oral or customary approval; promised goods/services; payment terms; customer credit information; expected concessions; cancellation rights. | I3: Do not convert “probable” into a mechanical percentage threshold. Collectibility is assessed against the consideration the entity expects to be entitled to, including the effect of price concessions. Enforceability depends on applicable law. | J3: At contract inception and whenever Revenue Compass must determine whether Step 1 is satisfied. | K3: Whether each of the five criteria appears satisfied; supporting contract evidence; missing evidence; a draft overall qualifies/does-not-qualify conclusion. | L3: Each criterion and the final Step 1 conclusion, including collectibility and any legal-enforceability assumptions. | M3: Treat the five criteria as blocking conditions for finalized ASC 606 analysis. Preserve entered facts even if criteria fail; do not calculate authoritative ASC 606 revenue for a failed Step 1 contract. | N3: FASB ASC; Deloitte Revenue Recognition Roadmap §4.3 | O3: https://asc.fasb.org/ https://dart.deloitte.com/USDART/home/codification/revenue/asc606-10/roadmap-revenue-recognition/chapter-4-step-1-identify-contract/4-3-criteria-for-identifying-a | P3: step1, contract criteria, approval, rights, payment terms, commercial substance, collectibility | Q3: Approved | R3: 46270
A4: 2 | B4: Step 1 | C4: Enforceable Rights and Obligations | D4: ASC 606-10-25-2 | E4: ASC 606-10-25-1; ASC 606-10-25-3 through 25-4 | F4: A contract may be written, oral, or implied by customary business practices, but ASC 606 applies only to the period in which enforceable rights and obligations exist. | G4: 1. Identify the form of the agreement. 2. Determine whether enforceable rights and obligations exist under applicable law. 3. Identify any provisions that make promises or payment rights unenforceable. | H4: Contract form; governing law; signatures/approvals; customary practices; purchase orders; order acceptance process; cancellation clauses; legal advice where necessary. | I4: Accounting form does not override legal enforceability. Oral or implied contracts can qualify. Revenue Compass should flag legal questions rather than infer enforceability from commercial intent alone. | J4: When an arrangement is unsigned, oral, subject to customary practices, or contains unusual termination/enforceability terms. | K4: Contract form, apparent evidence of approval, identified rights/obligations, and an “uncertain” flag when legal enforceability cannot be established from supplied materials. | L4: Any legal-enforceability conclusion or assumption that affects the contract term or Step 1 qualification. | M4: Store enforceability as an accountant-approved judgment; do not infer legal conclusions deterministically. | N4: FASB ASC; Deloitte Revenue Recognition Roadmap §4.2 | O4: https://asc.fasb.org/ https://dart.deloitte.com/USDART/home/codification/revenue/asc606-10/roadmap-revenue-recognition/chapter-4-step-1-identify-contract/4-2-identifying-a-contract-with | P4: step1, enforceability, written contract, oral contract, implied contract, governing law | Q4: Approved | R4: 46270
A5: 3 | B5: Step 1 | C5: Contract Term — Enforceable Period | D5: ASC 606-10-25-3 | E5: ASC 606-10-25-2; ASC 606-10-25-4 | F5: The accounting contract term is the period during which the parties have present enforceable rights and obligations, which may differ from the stated legal term when substantive termination rights exist. | G5: 1. Identify stated start/end dates. 2. Identify termination and renewal provisions. 3. Determine the enforceable period after considering unilateral cancellation rights and substantive penalties. 4. Separate customer options for future periods when appropriate. | H5: Stated term; auto-renewal provisions; notice periods; cancellation fees; refund rights; nonrefundable amounts; renewal pricing; governing-law information. | I5: A stated multi-year term does not automatically establish a multi-year accounting term if either party can terminate without substantive compensation. Conversely, substantive termination penalties may support a longer enforceable term. | J5: At inception, renewal, or modification when the enforceable contract period affects performance obligations, transaction price, or recognition. | K5: Proposed enforceable start/end dates, identified cancellation rights, and rationale based on supplied clauses. | L5: The enforceable contract term and treatment of renewal/cancellation options. | M5: Use approved enforceable dates as boundaries for core contract analysis; warn when PO recognition dates fall outside that term unless supported by another approved lifecycle segment. | N5: FASB ASC; Deloitte Revenue Recognition Roadmap §4.4 | O5: https://asc.fasb.org/ https://dart.deloitte.com/USDART/home/codification/revenue/asc606-10/roadmap-revenue-recognition/chapter-4-step-1-identify-contract/4-4-contract-term | P5: step1, contract term, termination, cancellation, enforceable period, renewal | Q5: Approved | R5: 46270
A6: 4 | B6: Step 1 | C6: Wholly Unperformed Contract — Free Termination | D6: ASC 606-10-25-4 | E6: ASC 606-10-25-2 through 25-3 | F6: A contract does not exist for ASC 606 purposes when it is wholly unperformed and each party can unilaterally terminate it without compensating the other party. | G6: 1. No promised goods or services have been transferred. 2. The entity has not received, and is not entitled to receive, consideration. 3. Each party can terminate without compensating the other party. | H6: Performance to date; cash received; payment entitlement; termination rights; deposits; cancellation penalties. | I6: All conditions matter. A contract may cease to be “wholly unperformed” once either transfer or payment entitlement arises. A substantive penalty can create enforceability even before performance. | J6: When assessing unsigned orders, cancellable SaaS subscriptions, trial periods, or agreements awaiting activation. | K6: Whether the contract appears wholly unperformed and freely terminable, with cited clauses/facts. | L6: Final conclusion on whether an ASC 606 contract presently exists. | M6: If approved as freely terminable and wholly unperformed, block contract finalization until circumstances change. | N6: FASB ASC; Deloitte Revenue Recognition Roadmap §4.4 | O6: https://asc.fasb.org/ https://dart.deloitte.com/USDART/home/codification/revenue/asc606-10/roadmap-revenue-recognition/chapter-4-step-1-identify-contract/4-4-contract-term | P6: step1, wholly unperformed, termination without compensation, free cancellation | Q6: Approved | R6: 46270
A7: 5 | B7: Step 1 | C7: Reassessment After Contract Criteria Are Met | D7: ASC 606-10-25-5 | E7: ASC 606-10-25-1 | F7: Once the Step 1 criteria are met, they are not reassessed unless a significant change in facts and circumstances indicates that reassessment is necessary. | G7: 1. Confirm the contract previously qualified. 2. Identify a significant change in facts/circumstances. 3. Reassess the affected criteria, particularly collectibility, for remaining consideration and performance. | H7: Original approval date; customer credit events; bankruptcy/liquidity events; payment history; changes in legal enforceability; remaining performance and consideration. | I7: Routine payment delays or minor credit changes do not automatically reopen Step 1. Credit losses on unconditional receivables are generally addressed under ASC 326 rather than by reversing revenue solely because collection risk later increases. | J7: During ongoing contract monitoring when a major customer credit or legal event occurs. | K7: Whether facts appear significant enough to require reassessment and which Step 1 criterion is affected. | L7: Whether reassessment is required and the revised conclusion. | M7: Preserve the original approved Step 1 assessment and record a dated reassessment rather than overwriting history. | N7: FASB ASC; Deloitte Revenue Recognition Roadmap §4.5 | O7: https://asc.fasb.org/ https://dart.deloitte.com/USDART/home/codification/revenue/asc606-10/roadmap-revenue-recognition/chapter-4-step-1-identify-contract/4-5-reassessing-criteria-for-identifying | P7: step1, reassessment, collectibility change, bankruptcy, significant change | Q7: Approved | R7: 46270
A8: 6 | B8: Step 1 | C8: Continuing Assessment When Criteria Initially Fail | D8: ASC 606-10-25-6 | E8: ASC 606-10-25-1; ASC 606-10-25-7 through 25-8 | F8: If an arrangement initially fails the Step 1 criteria, the entity continues to assess the arrangement and applies ASC 606 once the criteria are subsequently met. | G8: 1. Identify failed criteria. 2. Continue monitoring facts and circumstances. 3. Determine the date on which all Step 1 criteria are first satisfied. 4. Until then, apply the guidance for consideration received before a qualifying contract exists. | H8: Failed criteria; subsequent approvals; payment/collection developments; revised terms; performance status; consideration received. | I8: A failed Step 1 assessment is not necessarily permanent. Revenue recognition does not begin merely because cash is received or performance occurs if the contract criteria remain unsatisfied. | J8: When onboarding high-risk customers or arrangements that become enforceable/collectible only after later events. | K8: Which criteria remain unresolved and whether new evidence appears to cure them. | L8: The date all criteria become satisfied and any prior nonqualifying-period treatment. | M8: Maintain Step 1 status as pending/failed until accountant approval of a later qualifying assessment. | N8: FASB ASC; Deloitte Revenue Recognition Roadmap §4.5 | O8: https://asc.fasb.org/ https://dart.deloitte.com/USDART/home/codification/revenue/asc606-10/roadmap-revenue-recognition/chapter-4-step-1-identify-contract/4-5-reassessing-criteria-for-identifying | P8: step1, failed criteria, continuing assessment, later qualification | Q8: Approved | R8: 46270
A9: 7 | B9: Step 1 | C9: Consideration Received Before Contract Criteria Are Met | D9: ASC 606-10-25-7 | E9: ASC 606-10-25-6; ASC 606-10-25-8 | F9: When consideration is received before the Step 1 criteria are met, revenue is recognized only when the specified release conditions are satisfied; otherwise the amount remains a liability. | G9: Evaluate whether: (a) no remaining transfer obligations exist and all or substantially all consideration has been received and is nonrefundable; (b) the contract has been terminated and consideration received is nonrefundable; or (c) other conditions in the current guidance permit recognition after transfer and cessation of obligations. If none apply, continue liability accounting. | H9: Cash/noncash consideration received; refundability; remaining obligations; termination status; transfer history; enforceable claims. | I9: Do not use a fixed numerical bright line for “substantially all.” A contractual label such as “nonrefundable” does not by itself establish revenue if the entity still owes goods/services or the ASC 606 release conditions are not met. | J9: When deposits or prepayments are received from arrangements that do not yet qualify as contracts. | K9: Whether a release condition appears met, with explicit evidence and any unresolved legal/refundability questions. | L9: The release condition and recognition date, if any. | M9: Record/track the amount as a nonqualifying-arrangement liability until an approved release or later Step 1 qualification. | N9: FASB ASC; Deloitte Revenue Recognition Roadmap §4.6 | O9: https://asc.fasb.org/ https://dart.deloitte.com/USDART/home/codification/revenue/asc606-10/roadmap-revenue-recognition/chapter-4-step-1-identify-contract/4-6-consideration-received-when-criteria | P9: step1, consideration received, failed contract, nonrefundable, liability, release | Q9: Approved | R9: 46270
A10: 8 | B10: Step 1 | C10: Liability for Nonqualifying Arrangement | D10: ASC 606-10-25-8 | E10: ASC 606-10-25-6 through 25-7 | F10: Consideration received from a customer before an arrangement meets the Step 1 criteria is generally presented as a liability until the qualifying or release conditions are met. | G10: 1. Determine amount of consideration received. 2. Confirm Step 1 criteria are not met. 3. Confirm no 25-7 release condition is satisfied. 4. Continue liability presentation until status changes. | H10: Amounts received; payment dates; Step 1 status; refundability; remaining obligations. | I10: Use the amount received as the starting measurement; do not treat such deposits as revenue simply because the payment is contractually nonrefundable. | J10: Balance-sheet treatment of customer cash received before a valid ASC 606 contract exists. | K10: Proposed liability classification and a link to the unresolved Step 1 criteria. | L10: The classification/release of the liability. | M10: Keep this liability outside finalized ASC 606 revenue schedules until Step 1 becomes satisfied or release criteria are approved. | N10: FASB ASC; Deloitte Revenue Recognition Roadmap §4.6 | O10: https://asc.fasb.org/ https://dart.deloitte.com/USDART/home/codification/revenue/asc606-10/roadmap-revenue-recognition/chapter-4-step-1-identify-contract/4-6-consideration-received-when-criteria | P10: step1, nonqualifying arrangement, deposit liability, pre-contract cash | Q10: Approved | R10: 46270
A11: 9 | B11: Step 1 | C11: Combining Contracts | D11: ASC 606-10-25-9 | E11: ASC 606-10-25-14 through 25-22 | F11: Contracts entered into at or near the same time with the same customer or related parties are combined when they are negotiated as a package with one commercial objective, consideration in one depends on the other, or the promised goods/services form a single performance obligation. | G11: 1. Same customer or related parties. 2. Entered into at or near the same time. 3. At least one combination condition is met: single commercial objective, interdependent consideration, or promises together form one performance obligation. | H11: Execution dates; counterparties; negotiation history; cross-contract pricing; side letters; promises in each agreement; PO analysis. | I11: There is no universal day-count bright line for “at or near the same time.” Any one of the three economic conditions is sufficient. Legal document count does not determine the accounting unit. | J11: When a SaaS deal uses multiple order forms, SOWs, master agreements, reseller/customer documents, or near-simultaneous amendments. | K11: Potentially related contracts, which combination condition appears relevant, and evidence/uncertainty. | L11: Whether contracts are combined and the resulting combined contract population. | M11: If approved, merge the contracts for Steps 2–5 while preserving source-document provenance for each promise and payment term. | N11: FASB ASC; Deloitte Revenue Recognition Roadmap §4.7 | O11: https://asc.fasb.org/ https://dart.deloitte.com/USDART/home/codification/revenue/asc606-10/roadmap-revenue-recognition/chapter-4-step-1-identify-contract/4-7-combining-contracts | P11: step1, combine contracts, package, interdependent pricing, same customer, side agreements | Q11: Approved | R11: 46270
A12: 10 | B12: Step 1 | C12: Collectibility Versus Implicit Price Concession | D12: ASC 606-10-25-1(e) | E12: ASC 606-10-32-7; ASC 606-10-32-8 through 32-14 | F12: A lower amount expected to be collected can reflect either credit risk or an implicit price concession; the distinction affects the Step 1 collectibility analysis and the transaction price. | G12: 1. Determine amount the entity expects to be entitled to. 2. Identify whether accepting less than stated price is an expected concession or a credit loss on an unconditional amount. 3. Assess collectibility of the expected entitlement. | H12: Stated price; customary concessions; customer class; collection history; negotiations; credit data; subsequent payments; enforceable rights. | I12: A concession changes the amount of consideration in the transaction price; a credit loss generally does not. Subsequent cash shortfalls are not automatically evidence that the original price was variable. | J12: When a customer has weak credit, pricing is routinely negotiated after service, or collections differ from stated invoices. | K12: Whether facts indicate concession, credit risk, or uncertainty; proposed expected entitlement; missing evidence. | L12: Classification of the shortfall and collectibility conclusion. | M12: Do not automatically reduce revenue for collection shortfalls; route approved concessions into variable-consideration logic and credit losses outside the revenue engine. | N12: FASB ASC; Deloitte Revenue Recognition Roadmap Ch. 4 and §6.3 | O12: https://asc.fasb.org/ https://dart.deloitte.com/USDART/home/codification/revenue/asc606-10/roadmap-revenue-recognition/chapter-4-step-1-identify-contract/4-3-criteria-for-identifying-a https://dart.deloitte.com/USDART/home/codification/revenue/asc606-10/roadmap-revenue-recognition/chapter-6-step-3-determine-transaction/6-3-variable-consideration | P12: step1, collectibility, price concession, credit risk, expected entitlement | Q12: Approved | R12: 46270
A13: 11 | B13: Step 2 | C13: Identify Performance Obligations | D13: ASC 606-10-25-14 | E13: ASC 606-10-25-15 through 25-22 | F13: At contract inception, each promise is evaluated to identify performance obligations consisting of a distinct good/service or a qualifying series of distinct goods/services that are substantially the same and have the same pattern of transfer. | G13: 1. Identify promised goods/services. 2. Apply the distinct test. 3. Combine non-distinct promises until a distinct bundle results. 4. Apply the series guidance when applicable. | H13: Contract promises; implied promises; customer benefit; integration/customization/interdependence facts; series facts; service pattern. | I13: Performance obligations are accounting units, not necessarily invoice lines or SOW headings. A single PO can contain multiple non-distinct promises; a series of individually distinct services can also be one PO. | J13: For every qualifying contract before allocating transaction price. | K13: Candidate promises, candidate PO groupings, distinct/series analysis, and supporting evidence. | L13: Final promise list, grouping, PO classification, and rationale. | M13: Allow accountant-approved grouping only; deterministic engine uses the approved POs and never decides distinctness. | N13: FASB ASC; Deloitte Revenue Recognition Roadmap §5.3 | O13: https://asc.fasb.org/ https://dart.deloitte.com/USDART/home/codification/revenue/asc606-10/roadmap-revenue-recognition/chapter-5-step-2-identify-performance/5-3-identifying-performance-obligations-in | P13: step2, performance obligation, promise, distinct, bundle, series | Q13: Approved | R13: 46270
A14: 12 | B14: Step 2 | C14: Series of Distinct Goods or Services | D14: ASC 606-10-25-14(b) | E14: ASC 606-10-25-15; ASC 606-10-25-27; ASC 606-10-25-31 through 25-32 | F14: A qualifying series of distinct goods/services is accounted for as one performance obligation when the items are substantially the same and have the same pattern of transfer. | G14: 1. Each increment is distinct. 2. Items are substantially the same. 3. Each increment would satisfy the same over-time criterion. 4. The same method would measure progress for each increment. | H14: Nature of recurring service; transfer pattern; service periods; over-time basis; measure of progress; customer benefit. | I14: The series provision is mandatory when its criteria are met. Individual series elements remain relevant for variable-consideration allocation and modifications even though the series is one PO. | J14: Recurring SaaS, hosting, transaction processing, managed services, daily/weekly stand-ready services. | K14: Whether series criteria appear met, the underlying distinct service increment, and rationale. | L14: Series classification, underlying increment, and progress method. | M14: Store PO kind/classification as series; enable series-period allocation only after accountant approval of the relevant variable-consideration exception. | N14: FASB ASC; Deloitte Revenue Recognition Roadmap §5.3 | O14: https://asc.fasb.org/ https://dart.deloitte.com/USDART/home/codification/revenue/asc606-10/roadmap-revenue-recognition/chapter-5-step-2-identify-performance/5-3-identifying-performance-obligations-in | P14: step2, series, substantially same, same pattern, recurring service, SaaS | Q14: Approved | R14: 46270
... A118: 116 | B118: Special Topics / Industry Applications | C118: Portfolio Practical Expedient | D118: ASC 606-10-10-4 | E118: ASC 606-10-05-4 | F118: ASC 606 may be applied to a portfolio of contracts or performance obligations with similar characteristics when the entity reasonably expects the financial-statement effects would not differ materially from applying the guidance to individual contracts or performance obligations. | G118: 1. Define portfolio and similar characteristics. 2. Assess expected difference from individual-contract accounting. 3. Document why the difference would not be material. 4. Apply estimates/assumptions that reflect portfolio size/composition. | H118: Contract population; similarity criteria; expected outcomes; materiality analysis; sampling/analytics; policy. | I118: This is a practical expedient, not permission to ignore contract-specific terms that create materially different outcomes. Revenue Compass currently analyzes individual contract lifecycles unless a future portfolio module is added. | J118: High-volume homogeneous customer contracts, consumer subscriptions, standardized transactions. | K118: Whether a population appears suitable for portfolio treatment and what characteristics support similarity. | L118: Policy election and materiality assessment. | M118: No automated portfolio accounting in current scope; retain as reference and future expansion point. | N118: FASB ASC; Deloitte Revenue Recognition Roadmap overview | O118: https://asc.fasb.org/ https://dart.deloitte.com/USDART/home/codification/revenue/asc606-10/roadmap-revenue-recognition | P118: portfolio practical expedient, similar contracts, materiality, high volume | Q118: Approved | R118: 46270

Sheet Sources
A1: Source Index
A2: Source ID | B2: Authority Level | C2: Publisher | D2: Source / Section | E2: Use in Library | F2: URL | G2: Last Checked
A3: S-001 | B3: Authoritative | C3: FASB | D3: Accounting Standards Codification / Standards | E3: Official source of authoritative nongovernmental U.S. GAAP. Use the Codification paragraph references in each card as the primary authority. | F3: https://www.fasb.org/standards | G3: 2026-09-04
A4: S-002 | B4: Authoritative access | C4: FASB | D4: Accounting Standards Codification Basic View | E4: Access point for ASC research. Do not reproduce substantial copyrighted Codification text in the library; use original paraphrases and paragraph references. | F4: https://asc.fasb.org/ | G4: 2026-09-04
A5: S-010 | B5: Interpretive | C5: Deloitte | D5: Revenue Recognition Roadmap — Main | E5: Comprehensive nonauthoritative interpretation of ASC 606, ASC 340-40 and related implementation issues. | F5: https://dart.deloitte.com/USDART/home/codification/revenue/asc606-10/roadmap-revenue-recognition | G5: 2026-09-04
A6: S-011 | B6: Interpretive | C6: Deloitte | D6: Step 1 — Identify the Contract | E6: Contract criteria, enforceability, term, reassessment, failed contracts and combining contracts. | F6: https://dart.deloitte.com/USDART/home/codification/revenue/asc606-10/roadmap-revenue-recognition/chapter-4-step-1-identify-contract | G6: 2026-09-04
A7: S-012 | B7: Interpretive | C7: Deloitte | D7: Step 2 — Promises in Contracts | E7: Explicit/implied promises, fulfillment activities, immaterial promises and shipping/handling. | F7: https://dart.deloitte.com/USDART/home/codification/revenue/asc606-10/roadmap-revenue-recognition/chapter-5-step-2-identify-performance/5-2-promises-in-contracts-with | G7: 2026-09-04
A8: S-013 | B8: Interpretive | C8: Deloitte | D8: Step 2 — Identifying Performance Obligations | E8: Distinctness, series guidance and unit-of-account analysis. | F8: https://dart.deloitte.com/USDART/home/codification/revenue/asc606-10/roadmap-revenue-recognition/chapter-5-step-2-identify-performance/5-3-identifying-performance-obligations-in | G8: 2026-09-04
A9: S-014 | B9: Interpretive | C9: Deloitte | D9: Step 2 — Nature of the Promise | E9: Stand-ready obligations and defining recurring service promises. | F9: https://dart.deloitte.com/USDART/home/codification/revenue/asc606-10/roadmap-revenue-recognition/chapter-5-step-2-identify-performance/5-4-defining-nature-promise | G9: 2026-09-04
A10: S-015 | B10: Interpretive | C10: Deloitte | D10: Nonrefundable Upfront Fees | E10: Upfront-fee analysis and relation to future services/material rights. | F10: https://dart.deloitte.com/USDART/home/codification/revenue/asc606-10/roadmap-revenue-recognition/chapter-5-step-2-identify-performance/5-6-nonrefundable-up-front-fees | G10: 2026-09-04
A11: S-016 | B11: Interpretive / industry | C11: Deloitte | D11: Implementation Services in Cloud-Based Hosted Software | E11: Technology-specific hosted-software implementation analysis. | F11: https://dart.deloitte.com/USDART/home/publications/deloitte/industry/technology/technology-alerts-applying-revenue-standard/implementation-services-cloud-based-hosted-software | G11: 2026-09-04
A12: S-020 | B12: Interpretive | C12: Deloitte | D12: Step 3 — Determine the Transaction Price | E12: Transaction price framework. | F12: https://dart.deloitte.com/USDART/home/codification/revenue/asc606-10/roadmap-revenue-recognition/chapter-6-step-3-determine-transaction | G12: 2026-09-04
A13: S-021 | B13: Interpretive | C13: Deloitte | D13: Variable Consideration | E13: Identification, estimation methods, constraint and remeasurement. | F13: https://dart.deloitte.com/USDART/home/codification/revenue/asc606-10/roadmap-revenue-recognition/chapter-6-step-3-determine-transaction/6-3-variable-consideration | G13: 2026-09-04
... A34: S-070 | B34: Interpretive | C34: EY | D34: Financial Reporting Developments — Revenue from Contracts with Customers | E34: Alternative comprehensive nonauthoritative ASC 606 reference for cross-checking interpretations. | F34: https://www.ey.com/en_us/technical/accountinglink/financial-reporting-developments---revenue-from-contracts-with-c | G34: 2026-09-04

Sheet Phase 5B Map
A1: Phase 5B — Variable Consideration Requirements Traceability
A2: Approved design requirements mapped to this library. Item numbers are derived from matching guidance-card subtopics so the map stays readable even if cards are reordered.
A4: Requirement | B4: Supporting Guidance Cards | C4: Supporting Item Nos. | D4: Approved Revenue Compass Treatment | E4: Review Status
A5: Detect variable consideration only when relevant | B5: Variable Consideration — Identification | C5: 27 | D5: AI proposes present / absent / uncertain based on contract evidence. Accountant confirms/overrides. Manual mode uses an explicit Yes/No trigger; the detailed component UI remains collapsed when not relevant. | E5: Design approved; guidance card review pending
A6: Support expected value method | B6: Expected Value Method | C6: 28 | D6: Accountant approves method/outcomes/probabilities; deterministic engine performs probability-weighted money calculation. | E6: Design approved; guidance card review pending
A7: Support most likely amount method | B7: Most Likely Amount Method | C7: 29 | D7: Accountant approves method and most-likely outcome; do not probability-weight a binary outcome unless expected-value method is selected. | E7: Design approved; guidance card review pending
A8: Keep estimation method consistent by component | B8: Consistency of Variable-Consideration Estimation Method | C8: 30 | D8: Phase 5B locks the approved method for each component and uses dated remeasurement events. | E8: Design approved; guidance card review pending
A9: Constraint is accountant judgment, not a probability haircut | B9: Variable Consideration Constraint; Constraint — Reversal Risk Factors | C9: 32, 33 | D9: Engine computes unconstrained estimate. Accountant enters constrained amount included. Engine validates range and derives excluded/partial/full status. | E9: Design approved; guidance card review pending
A10: Remeasure estimated variable consideration over time | B10: Remeasurement of Variable Consideration; Allocating Subsequent Transaction-Price Changes | C10: 34, 56 | D10: Preserve original assessment and dated updates. Compute delta and cumulative catch-up deterministically. | E10: Design approved; guidance card review pending
A11: Allow multiple variable-consideration components | B11: Variable Consideration — Identification | C11: 27 | D11: Each component has its own treatment, method/usage meters, constraint if estimated, allocation treatment, rationale, evidence and lifecycle history. | E11: Design approved; guidance card review pending
A12: General vs specific PO allocation | B12: Variable Consideration — What It Relates To; Variable Consideration Allocation Exception | C12: 52, 53 | D12: Approved allocation treatment is general or specific_po. 32-40 requires both “relates specifically” and “consistent with allocation objective.” | E12: Design approved; guidance card review pending
A13: Specific distinct service period within a series | B13: Variable Consideration Allocation Exception; SaaS — Usage-Based Variable Consideration Within a Series | C13: 53, 107 | D13: Approved allocation treatment specific_series_period is available only for qualifying series and approved 32-40 criteria. | E13: Design approved; guidance card review pending
A14: Qualifying simple usage recognized as incurred | B14: SaaS — Usage-Based Variable Consideration Within a Series | C14: 107 | D14: Future qualifying usage is not forecast into inception TP. Actual usage increases lifecycle consideration and related-period revenue as incurred. | E14: Design approved; guidance card review pending
A15: Multiple fixed-rate usage meters with exact ratios | B15: AI/API Token Pricing — Multiple Fixed-Rate Meters | C15: 108 | D15: Represent price as exact amount per quantity (e.g., $4.00 per 1,000,000 tokens); compute with integer cents/BigInt, not floating-point fractional cents. | E15: Design approved; guidance card review pending
... A18: Case 7 — AtlasData/TitanEnergy acceptance case | B18: Most Likely Amount Method; Variable Consideration Constraint; Variable Consideration Allocation Exception; Point-in-Time Recognition | C18: 29, 32, 53, 67 | D18: Fixed consideration $460,000. $30,000 completion bonus is a binary VC component; most-likely amount can be $30,000, full constraint inclusion if approved, total TP $490,000. Fixed pool allocates by SSP ($55,200 implementation / $404,800 SaaS); bonus allocates specifically to implementation if 32-40 is approved, producing $85,200 implementation / $404,800 SaaS. Implementation is point-in-time on 3/20/2027 when no 25-27 criterion is met; lack of enforceable right to payment means 25-27(c) fails regardless of alternative use. Bonus inclusion does not create AR before the right is unconditional. | E18: Design approved; guidance card review pending

Sheet Coverage
A1: Library Coverage & Review Dashboard
A3: Topic | B3: Cards | C3: Draft | D3: Reviewed | E3: Approved | F3: Needs revision
A4: Step 1 | B4: =COUNTIF('Guidance Cards'!$B$3:$B$118,A4) -> 10 | C4: =COUNTIFS('Guidance Cards'!$B$3:$B$118,A4,'Guidance Cards'!$Q$3:$Q$118,"Draft*") -> 0 | D4: =COUNTIFS('Guidance Cards'!$B$3:$B$118,A4,'Guidance Cards'!$Q$3:$Q$118,"Reviewed") -> 0 | E4: =COUNTIFS('Guidance Cards'!$B$3:$B$118,A4,'Guidance Cards'!$Q$3:$Q$118,"Approved") -> 10 | F4: =COUNTIFS('Guidance Cards'!$B$3:$B$118,A4,'Guidance Cards'!$Q$3:$Q$118,"Needs revision") -> 0
A5: Step 2 | B5: =COUNTIF('Guidance Cards'!$B$3:$B$118,A5) -> 14 | C5: =COUNTIFS('Guidance Cards'!$B$3:$B$118,A5,'Guidance Cards'!$Q$3:$Q$118,"Draft*") -> 0 | D5: =COUNTIFS('Guidance Cards'!$B$3:$B$118,A5,'Guidance Cards'!$Q$3:$Q$118,"Reviewed") -> 0 | E5: =COUNTIFS('Guidance Cards'!$B$3:$B$118,A5,'Guidance Cards'!$Q$3:$Q$118,"Approved") -> 14 | F5: =COUNTIFS('Guidance Cards'!$B$3:$B$118,A5,'Guidance Cards'!$Q$3:$Q$118,"Needs revision") -> 0
A6: Step 3 | B6: =COUNTIF('Guidance Cards'!$B$3:$B$118,A6) -> 19 | C6: =COUNTIFS('Guidance Cards'!$B$3:$B$118,A6,'Guidance Cards'!$Q$3:$Q$118,"Draft*") -> 0 | D6: =COUNTIFS('Guidance Cards'!$B$3:$B$118,A6,'Guidance Cards'!$Q$3:$Q$118,"Reviewed") -> 0 | E6: =COUNTIFS('Guidance Cards'!$B$3:$B$118,A6,'Guidance Cards'!$Q$3:$Q$118,"Approved") -> 19 | F6: =COUNTIFS('Guidance Cards'!$B$3:$B$118,A6,'Guidance Cards'!$Q$3:$Q$118,"Needs revision") -> 0
A7: Step 4 | B7: =COUNTIF('Guidance Cards'!$B$3:$B$118,A7) -> 14 | C7: =COUNTIFS('Guidance Cards'!$B$3:$B$118,A7,'Guidance Cards'!$Q$3:$Q$118,"Draft*") -> 0 | D7: =COUNTIFS('Guidance Cards'!$B$3:$B$118,A7,'Guidance Cards'!$Q$3:$Q$118,"Reviewed") -> 0 | E7: =COUNTIFS('Guidance Cards'!$B$3:$B$118,A7,'Guidance Cards'!$Q$3:$Q$118,"Approved") -> 14 | F7: =COUNTIFS('Guidance Cards'!$B$3:$B$118,A7,'Guidance Cards'!$Q$3:$Q$118,"Needs revision") -> 0
A8: Step 5 | B8: =COUNTIF('Guidance Cards'!$B$3:$B$118,A8) -> 20 | C8: =COUNTIFS('Guidance Cards'!$B$3:$B$118,A8,'Guidance Cards'!$Q$3:$Q$118,"Draft*") -> 0 | D8: =COUNTIFS('Guidance Cards'!$B$3:$B$118,A8,'Guidance Cards'!$Q$3:$Q$118,"Reviewed") -> 0 | E8: =COUNTIFS('Guidance Cards'!$B$3:$B$118,A8,'Guidance Cards'!$Q$3:$Q$118,"Approved") -> 20 | F8: =COUNTIFS('Guidance Cards'!$B$3:$B$118,A8,'Guidance Cards'!$Q$3:$Q$118,"Needs revision") -> 0
A9: Special Topics / Industry Applications | B9: =COUNTIF('Guidance Cards'!$B$3:$B$118,A9) -> 39 | C9: =COUNTIFS('Guidance Cards'!$B$3:$B$118,A9,'Guidance Cards'!$Q$3:$Q$118,"Draft*") -> 0 | D9: =COUNTIFS('Guidance Cards'!$B$3:$B$118,A9,'Guidance Cards'!$Q$3:$Q$118,"Reviewed") -> 0 | E9: =COUNTIFS('Guidance Cards'!$B$3:$B$118,A9,'Guidance Cards'!$Q$3:$Q$118,"Approved") -> 39 | F9: =COUNTIFS('Guidance Cards'!$B$3:$B$118,A9,'Guidance Cards'!$Q$3:$Q$118,"Needs revision") -> 0
A11: Total | B11: =SUM(B4:B9) -> 116 | C11: =SUM(C4:C9) -> 0 | D11: =SUM(D4:D9) -> 0 | E11: =SUM(E4:E9) -> 116 | F11: =SUM(F4:F9) -> 0
A13: Phase 5B mapped requirements | B13: 14
A14: Prepared date | B14: 2026-09-04

Sheet Taxonomy
A1: Field Dictionary & Controlled Values
A3: Field / Value | B3: Type | C3: Meaning | D3: Implementation Notes
A4: Item No. | B4: Stable identifier | C4: Sequential study/reference ID. | D4: Do not renumber simply because you insert a new card in the future; append new IDs or deliberately version the library.
A5: Topic | B5: Controlled category | C5: Step 1, Step 2, Step 3, Step 4, Step 5, or Special Topics / Industry Applications. | D5: Primary retrieval/filter category.
A6: Subtopic | B6: Decision name | C6: One meaningful accounting decision or application. | D6: More useful for retrieval than one row per Codification paragraph.
A7: Primary ASC Reference | B7: Authority pointer | C7: Main paragraph(s) underlying the card. | D7: Authoritative source; verify before card approval.
A8: Related ASC References | B8: Authority pointers | C8: Other paragraphs needed for context, exceptions or downstream accounting. | D8: Semicolon-delimited.
A9: Rule Summary | B9: Original synthesis | C9: Concise plain-English statement of the accounting principle. | D9: Paraphrase; do not reproduce substantial copyrighted ASC text.
A10: Decision Criteria | B10: Decision framework | C10: Questions/tests the accountant and AI should evaluate. | D10: Should be specific enough to drive review UI.
A11: Facts Required | B11: Evidence requirements | C11: Contract or management facts needed to reach a supportable proposal. | D11: Missing facts should trigger uncertainty rather than fabrication.
A12: Important Nuances | B12: Interpretive cautions | C12: Exceptions, common errors, boundaries and distinctions. | D12: Often the highest-value retrieval field for avoiding simplistic conclusions.
A13: When Relevant | B13: Retrieval trigger | C13: Fact patterns that should cause the card to be retrieved. | D13: Use with Retrieval Tags.
A14: AI May Propose | B14: AI boundary | C14: Facts/judgments/rationale AI may prepopulate. | D14: Always pending accountant approval unless purely deterministic downstream calculation.
... A29: expected_value | B29: VC estimation method | C29: Probability-weighted sum of outcomes. | D29: Deterministic engine computes from approved amounts/probabilities.
